nua/build/__init__.py
nua/build/__main__.py
nua/build/autobuild/README.md
nua/build/autobuild/__init__.py
nua/build/autobuild/builders/Dockerfile_nua_builder_node16
nua/build/autobuild/builders/Dockerfile_nua_builder_node18
nua/build/autobuild/builders/Dockerfile_nua_builder_node20
nua/build/autobuild/builders/Dockerfile_nua_builder_ruby27
nua/build/autobuild/builders/Dockerfile_nua_builder_ruby31
nua/build/autobuild/builders/Dockerfile_nua_builder_ruby32
nua/build/autobuild/builders/__init__.py
nua/build/autobuild/builders/node16.json
nua/build/autobuild/builders/node18.json
nua/build/autobuild/builders/node20.json
nua/build/autobuild/builders/ruby27.json
nua/build/autobuild/builders/ruby31.json
nua/build/autobuild/builders/ruby32.json
nua/build/autobuild/constants.py
nua/build/autobuild/dockerfiles/Dockerfile_nua_builder_slim
nua/build/autobuild/dockerfiles/Dockerfile_nua_python_slim
nua/build/autobuild/dockerfiles/__init__.py
nua/build/autobuild/main.py
nua/build/autobuild/nua_image_builder.py
nua/build/autobuild/nua_wheel_builder.py
nua/build/autobuild/register_builders.py
nua/build/builders/__init__.py
nua/build/builders/base.py
nua/build/builders/docker.py
nua/build/builders/factory.py
nua/build/builders/wrap.py
nua/build/config.py
nua/build/default_conf/__init__.py
nua/build/default_conf/config.toml
nua/build/defaults/Dockerfile
nua/build/defaults/__init__.py
nua/build/main.py
nua/build/module_definitions.py
nua/build/provider_modules/__init__.py
nua/build/provider_modules/mariadb.toml
nua/build/provider_modules/mongo.toml
nua/build/provider_modules/postgres.toml
nua/build/provider_modules/redis-cache.toml
nua/build/provider_modules/sqlite.toml
nua/build/scripts/__init__.py
nua/build/scripts/test_replace_domain.py
nua/build/version.py
nua_build-0.5.43.dist-info/METADATA
nua_build-0.5.43.dist-info/WHEEL
nua_build-0.5.43.dist-info/entry_points.txt
nua_build-0.5.43.dist-info/RECORD
