Metadata-Version: 2.1
Name: nua-build
Version: 0.5.43
Summary: Nua build package (currently: build, core build, agent)
Home-page: https://github.com/abilian/nua
License: Apache-2.0
Author: Stefane Fermigier
Author-email: sf@abilian.com
Requires-Python: >=3.10,<4.0
Classifier: Development Status :: 3 - Alpha
Classifier: Environment :: Console
Classifier: Intended Audience :: Developers
Classifier: License :: OSI Approved :: Apache Software License
Classifier: Programming Language :: Python :: 3
Classifier: Programming Language :: Python :: 3.10
Classifier: Programming Language :: Python :: 3.11
Requires-Dist: cleez (>=0.1.8,<0.2.0)
Requires-Dist: docker[ssh] (>=6.0.1,<7.0.0)
Requires-Dist: nua-lib (==0.5.43)
Requires-Dist: packaging (>=23.1,<24.0)
Requires-Dist: pydantic (>=1.10.8,<2.0.0)
Requires-Dist: snoop (>=0.4.3,<0.5.0)
Requires-Dist: tomli (>=2.0.1,<3.0.0)
Requires-Dist: tomli-w (>=1.0.0,<2.0.0)
Requires-Dist: typer[all] (>=0.7.0,<0.8.0)
Project-URL: Documentation, https://nua.rocks/
Project-URL: Repository, https://github.com/abilian/nua
